setup.py
hipchat/__init__.py
hipchat/api.py
hipchat/data.py
hipchat/messages.py
hipchat/rooms.py
hipchat/users.py
hipchat_api.egg-info/PKG-INFO
hipchat_api.egg-info/SOURCES.txt
hipchat_api.egg-info/dependency_links.txt
hipchat_api.egg-info/top_level.txt