Metadata-Version: 1.1
Name: hipchat-api
Version: 0.0.2
Summary: A Pythonic wrapper for the HipChat API
Home-page: http://goodcode.io/
Author: Senko Rasic
Author-email: senko.rasic@goodcode.io
License: MIT
Platform: UNKNOWN
Classifier: Development Status :: 4 - Beta
Classifier: Environment :: Web Environment
Classifier: Intended Audience :: Developers
Classifier: License :: OSI Approved :: MIT License
Classifier: Programming Language :: Python
Classifier: Topic :: Software Development :: Libraries :: Python Modules
